[
    {
        "uuid": "8258de80-e589-4c39-9bd3-36f80c39166c",
        "userDefinedKey": "7ac9ba3b-1675-4b93-d169-7dc49958c11e",
        "concept": "Pennatula",
        "height": 100,
        "observer": "lonny",
        "width": 85,
        "x": 381,
        "y": 17,
        "rejected": false,
        "verified": false,
        "lastUpdatedTimestamp": "2023-09-14T20:23:02.560Z"
    },
    {
        "uuid": "e086a8da-e905-4361-8e08-d12933df9a8c",
        "userDefinedKey": "aacee171-ccb3-43a2-c569-7dc49958c11e",
        "concept": "Ophiuroidea",
        "height": 73,
        "observer": "yolov5",
        "width": 108,
        "x": 38,
        "y": 48,
        "rejected": false,
        "verified": false,
        "lastUpdatedTimestamp": "2023-09-14T20:23:02.560Z"
    },
    {
        "uuid": "6cad7d4e-a0c3-4ddb-971b-e200974e5dee",
        "userDefinedKey": "8e609059-9790-4bf5-d369-7dc49958c11e",
        "concept": "Pennatula",
        "height": 86,
        "observer": "lonny",
        "width": 75,
        "x": 225,
        "y": 19,
        "rejected": false,
        "verified": false,
        "lastUpdatedTimestamp": "2023-09-14T20:23:02.560Z"
    },
    {
        "uuid": "61484c5e-70b7-4f1a-8d87-cbb840d0841a",
        "userDefinedKey": "4076e150-173e-43b3-c969-7dc49958c11e",
        "concept": "Pennatula",
        "height": 91,
        "observer": "lonny",
        "width": 71,
        "x": 506,
        "y": 349,
        "rejected": false,
        "verified": false,
        "lastUpdatedTimestamp": "2023-09-14T20:23:02.560Z"
    },
    {
        "uuid": "2339295d-4523-4670-8f08-3a3faf698320",
        "userDefinedKey": "7d159e63-9527-4004-c769-7dc49958c11e",
        "concept": "Pennatula",
        "height": 78,
        "observer": "lonny",
        "width": 62,
        "x": 369,
        "y": 206,
        "rejected": false,
        "verified": false,
        "lastUpdatedTimestamp": "2023-09-14T20:23:02.560Z"
    },
    {
        "uuid": "b739d2da-8e80-45eb-a523-aec18ad986f4",
        "userDefinedKey": "b455613c-c1cf-4e82-cb69-7dc49958c11e",
        "concept": "Pennatula",
        "height": 114,
        "observer": "lonny",
        "width": 98,
        "x": 276,
        "y": 320,
        "rejected": false,
        "verified": false,
        "lastUpdatedTimestamp": "2023-09-14T20:23:02.560Z"
    },
    {
        "uuid": "1d8ee015-023d-46e3-8e1c-ee6e8fe45a74",
        "userDefinedKey": "160461ed-3def-4e8b-c169-7dc49958c11e",
        "concept": "Pennatula",
        "height": 52,
        "observer": "lonny",
        "width": 65,
        "x": 190,
        "y": 207,
        "rejected": false,
        "verified": false,
        "lastUpdatedTimestamp": "2023-09-14T20:23:02.560Z"
    },
    {
        "uuid": "9b3f7374-3e6d-4d59-b2b8-7e55612d6974",
        "userDefinedKey": "bc931249-ac04-44c9-c369-7dc49958c11e",
        "concept": "Pennatula",
        "height": 69,
        "observer": "lonny",
        "width": 65,
        "x": 615,
        "y": 78,
        "rejected": false,
        "verified": false,
        "lastUpdatedTimestamp": "2023-09-14T20:23:02.560Z"
    },
    {
        "uuid": "a39ba55b-47d8-47b1-ae78-aae3597c53e5",
        "userDefinedKey": "fe542da3-b4c3-4272-cd69-7dc49958c11e",
        "concept": "Pennatula",
        "height": 101,
        "observer": "lonny",
        "width": 51,
        "x": 5,
        "y": 384,
        "rejected": false,
        "verified": false,
        "lastUpdatedTimestamp": "2023-09-14T20:23:02.560Z"
    },
    {
        "uuid": "d75af0fe-e903-4f46-b8e8-fcc390739ccc",
        "userDefinedKey": "cc78fff5-3d83-4141-cf69-7dc49958c11e",
        "concept": "Ophiuroidea",
        "height": 92,
        "observer": "yolov5",
        "width": 208,
        "x": 368,
        "y": 140,
        "rejected": false,
        "verified": false,
        "lastUpdatedTimestamp": "2023-09-14T20:23:02.560Z"
    }
]