[
    {
        "uuid": "a3bf83a6-08ef-4c1f-8026-e382721a6712",
        "userDefinedKey": "8c038fe9-1b42-47cd-0064-dc6c5158c11e",
        "concept": "Terebellidae",
        "height": 74,
        "observer": "gsainz",
        "width": 71,
        "x": 1486,
        "y": 390,
        "rejected": false,
        "verified": false,
        "lastUpdatedTimestamp": "2023-09-14T20:21:00.384Z"
    },
    {
        "uuid": "859262f8-c0f3-496c-9120-80ac6557f736",
        "userDefinedKey": "48eeeaef-a5d5-4ade-1264-dc6c5158c11e",
        "concept": "Terebellidae",
        "height": 69,
        "observer": "gsainz",
        "width": 88,
        "x": 1609,
        "y": 599,
        "rejected": false,
        "verified": false,
        "lastUpdatedTimestamp": "2023-09-14T20:21:00.384Z"
    },
    {
        "uuid": "cbf7a1d0-961d-4163-b080-2549963ae2ac",
        "userDefinedKey": "9981a8d6-561c-409a-0e64-dc6c5158c11e",
        "concept": "Terebellidae",
        "height": 74,
        "observer": "gsainz",
        "width": 65,
        "x": 424,
        "y": 714,
        "rejected": false,
        "verified": false,
        "lastUpdatedTimestamp": "2023-09-14T20:21:00.384Z"
    },
    {
        "uuid": "fc93bab6-bd78-4bdf-8ff7-05ba11c90596",
        "userDefinedKey": "65ce9bb8-922a-4f28-0564-85aff603d41e",
        "concept": "Terebellidae",
        "height": 72,
        "observer": "lonny",
        "width": 69,
        "x": 1335,
        "y": 411,
        "rejected": false,
        "verified": false,
        "lastUpdatedTimestamp": "2023-09-14T20:21:00.384Z"
    },
    {
        "uuid": "8de2d90b-6a15-43fd-8744-43133769fb8f",
        "userDefinedKey": "bbc2c2be-36dc-45d6-fe63-dc6c5158c11e",
        "concept": "Terebellidae",
        "height": 83,
        "observer": "lonny",
        "width": 98,
        "x": 1223,
        "y": 302,
        "rejected": false,
        "verified": false,
        "lastUpdatedTimestamp": "2023-09-14T20:21:00.384Z"
    },
    {
        "uuid": "98e55a3d-43e9-4801-ba99-a772995ad9d9",
        "userDefinedKey": "48410774-ff48-44da-0c64-dc6c5158c11e",
        "concept": "Terebellidae",
        "height": 67,
        "observer": "gsainz",
        "width": 71,
        "x": 1160,
        "y": 306,
        "rejected": false,
        "verified": false,
        "lastUpdatedTimestamp": "2023-09-14T20:21:00.384Z"
    },
    {
        "uuid": "005ebbeb-5ef8-49d5-8bab-de9b82004f20",
        "userDefinedKey": "fb011bf3-9a57-45cb-546e-086f5158c11e",
        "concept": "Ophiuroidea",
        "height": 55,
        "observer": "yolov5",
        "width": 58,
        "x": 1470,
        "y": 895,
        "rejected": false,
        "verified": false,
        "lastUpdatedTimestamp": "2023-09-14T20:21:00.384Z"
    },
    {
        "uuid": "63c5d540-3f4a-42a0-b266-b78721c8df12",
        "userDefinedKey": "d6681f46-6e24-4ad7-586e-086f5158c11e",
        "concept": "Asteroidea",
        "height": 116,
        "observer": "yolov5",
        "width": 156,
        "x": 1529,
        "y": 226,
        "rejected": false,
        "verified": false,
        "lastUpdatedTimestamp": "2023-09-14T20:21:00.384Z"
    },
    {
        "uuid": "1d6c5eae-6bcc-499f-b1f4-2879f9658c7c",
        "userDefinedKey": "83f47d54-b538-4a56-566e-086f5158c11e",
        "concept": "Asteroidea",
        "height": 54,
        "observer": "yolov5",
        "width": 64,
        "x": 1088,
        "y": 414,
        "rejected": false,
        "verified": false,
        "lastUpdatedTimestamp": "2023-09-14T20:21:00.384Z"
    },
    {
        "uuid": "2bcdc949-be2e-4f09-96de-bd58e1b11c94",
        "userDefinedKey": "37b2d2ba-d62a-4757-5566-605af603d41e",
        "concept": "Terebellidae",
        "height": 64,
        "observer": "linda",
        "width": 64,
        "x": 1684,
        "y": 660,
        "rejected": false,
        "verified": false,
        "lastUpdatedTimestamp": "2023-09-14T20:21:00.384Z"
    },
    {
        "uuid": "36559fcf-abd8-4db6-8fc9-a82939851c6d",
        "userDefinedKey": "56ae3ac5-2225-41e6-0664-dc6c5158c11e",
        "concept": "Terebellidae",
        "height": 100,
        "observer": "gsainz",
        "width": 95,
        "x": 208,
        "y": 925,
        "rejected": false,
        "verified": false,
        "lastUpdatedTimestamp": "2023-09-14T20:21:00.384Z"
    }
]