[
    {
        "uuid": "88843719-4d4b-4e96-817a-3e74c8ce19dc",
        "userDefinedKey": "3175c4bd-08bb-4fe0-9261-6e1b1f1aae1e",
        "concept": "Ophiuroidea",
        "height": 86,
        "observer": "lonny",
        "width": 163,
        "x": 334,
        "y": 249,
        "rejected": false,
        "verified": false,
        "lastUpdatedTimestamp": "2021-09-29T21:30:55.441Z"
    },
    {
        "uuid": "74dbe795-7734-43e2-ba2e-cae793ea511c",
        "userDefinedKey": "9fb68587-fc16-448e-3767-c6c11e1aae1e",
        "concept": "Ophiuroidea",
        "height": 97,
        "observer": "lonny",
        "width": 145,
        "x": 137,
        "y": 684,
        "rejected": false,
        "verified": false,
        "lastUpdatedTimestamp": "2021-09-29T21:30:55.441Z"
    },
    {
        "uuid": "76d06d69-a2e8-4327-a137-af1ac64ac1a4",
        "userDefinedKey": "1f4ade1e-257e-4dfb-a568-398e1d1aae1e",
        "concept": "Ophiuroidea",
        "height": 67,
        "observer": "lonny",
        "width": 147,
        "x": 1048,
        "y": 627,
        "rejected": false,
        "verified": false,
        "lastUpdatedTimestamp": "2021-09-29T21:30:55.441Z"
    },
    {
        "uuid": "f4450337-0544-40ab-a40a-8236f2ef5006",
        "userDefinedKey": "f835c7b6-f4c8-43be-1365-f5671e1aae1e",
        "concept": "Ophiuroidea",
        "height": 65,
        "observer": "lonny",
        "width": 105,
        "x": 1000,
        "y": 920,
        "rejected": false,
        "verified": false,
        "lastUpdatedTimestamp": "2021-09-29T21:30:55.441Z"
    },
    {
        "uuid": "01381408-1b66-48a9-9de8-83b765c00ce0",
        "userDefinedKey": "70aae8e0-411b-4e05-4b65-783ae4f5aa1e",
        "concept": "Abyssocucumis abyssorum",
        "height": 110,
        "observer": "schlin",
        "width": 200,
        "x": 649,
        "y": 362,
        "rejected": false,
        "verified": false,
        "lastUpdatedTimestamp": "2021-09-29T21:30:55.441Z"
    },
    {
        "uuid": "07f6afd3-719c-4b17-a733-c2d10f4e8c9e",
        "userDefinedKey": "057e1c9e-d18c-44fa-3063-e2061e1aae1e",
        "concept": "Ophiuroidea",
        "height": 136,
        "observer": "lonny",
        "width": 182,
        "x": 1732,
        "y": 763,
        "rejected": false,
        "verified": false,
        "lastUpdatedTimestamp": "2021-09-29T21:30:55.441Z"
    }
]