[
    {
        "uuid": "fb28b9f9-83ca-4c9e-a696-cbb36d02b8bf",
        "userDefinedKey": "a0f9fdf7-27f5-4925-9b66-bac71658c11e",
        "concept": "Scotoplanes globosa",
        "height": 87,
        "observer": "yolov5",
        "width": 70,
        "x": 1300,
        "y": 228,
        "rejected": false,
        "verified": false,
        "lastUpdatedTimestamp": "2023-09-14T20:20:02.822Z"
    },
    {
        "uuid": "57bdaf7e-f476-4ea0-af98-ff0704725971",
        "userDefinedKey": "2767a4c6-e201-4bf6-816a-03c81658c11e",
        "concept": "Peniagone",
        "height": 71,
        "observer": "yolov5",
        "width": 113,
        "x": 1717,
        "y": 150,
        "rejected": false,
        "verified": false,
        "lastUpdatedTimestamp": "2023-09-14T20:20:02.822Z"
    },
    {
        "uuid": "82e2b860-cb50-49f1-bb77-772652139fe0",
        "userDefinedKey": "7ce8e599-26a5-425d-9d66-bac71658c11e",
        "concept": "Ophiuroidea",
        "height": 208,
        "observer": "yolov5",
        "width": 276,
        "x": 1376,
        "y": 621,
        "rejected": false,
        "verified": false,
        "lastUpdatedTimestamp": "2023-09-14T20:20:02.822Z"
    },
    {
        "uuid": "e41b09da-1f31-4306-a720-c913753a30ab",
        "userDefinedKey": "31f9f65f-b5a7-4b60-836a-03c81658c11e",
        "concept": "Peniagone",
        "height": 99,
        "observer": "yolov5",
        "width": 141,
        "x": 473,
        "y": 534,
        "rejected": false,
        "verified": false,
        "lastUpdatedTimestamp": "2023-09-14T20:20:02.822Z"
    },
    {
        "uuid": "19ccb247-c79f-4ef3-a01e-75bda0972f29",
        "userDefinedKey": "59e8c738-6212-4ae6-9f66-bac71658c11e",
        "concept": "Peniagone",
        "height": 71,
        "observer": "yolov5",
        "width": 125,
        "x": 1371,
        "y": 219,
        "rejected": false,
        "verified": false,
        "lastUpdatedTimestamp": "2023-09-14T20:20:02.822Z"
    }
]