[
    {
        "uuid": "2711467a-73c1-48a1-91e3-fc582e675edd",
        "userDefinedKey": "3b64ac4d-bb48-448b-b26b-1e9093b9a91e",
        "concept": "Liponema brevicorne",
        "height": 65,
        "observer": "linda",
        "width": 72,
        "x": 988,
        "y": 683,
        "rejected": false,
        "verified": false,
        "lastUpdatedTimestamp": "2021-09-29T21:16:17.340Z"
    },
    {
        "uuid": "5bf99fae-a255-43f8-bb1e-28c1cf7595b2",
        "userDefinedKey": "fe7191eb-c354-43a7-e56f-371fa63cbc1e",
        "concept": "Ophiuroidea",
        "height": 38,
        "observer": "gsainz",
        "width": 61,
        "x": 1384,
        "y": 896,
        "rejected": false,
        "verified": false,
        "lastUpdatedTimestamp": "2021-09-29T21:16:17.340Z"
    },
    {
        "uuid": "a67c9fed-5dca-4f3d-9fc9-6d35c593e5b2",
        "userDefinedKey": "d2fdc0a8-2909-4f87-d665-1b72a73cbc1e",
        "concept": "Ophiuroidea",
        "height": 46,
        "observer": "gsainz",
        "width": 43,
        "x": 887,
        "y": 977,
        "rejected": false,
        "verified": false,
        "lastUpdatedTimestamp": "2021-09-29T21:16:17.340Z"
    },
    {
        "uuid": "1df0c9bc-3212-41cd-afda-d3b7673929d7",
        "userDefinedKey": "448b12ee-3449-4da9-be69-3650a73cbc1e",
        "concept": "Ophiuroidea",
        "height": 50,
        "observer": "gsainz",
        "width": 46,
        "x": 1064,
        "y": 696,
        "rejected": false,
        "verified": false,
        "lastUpdatedTimestamp": "2021-09-29T21:16:17.340Z"
    },
    {
        "uuid": "e7bf89c2-eef8-47bb-86a2-6cb3a2d31151",
        "userDefinedKey": "f68bc535-aaca-443e-2663-4327a73cbc1e",
        "concept": "Ophiuroidea",
        "height": 43,
        "observer": "gsainz",
        "width": 66,
        "x": 816,
        "y": 783,
        "rejected": false,
        "verified": false,
        "lastUpdatedTimestamp": "2021-09-29T21:16:17.340Z"
    }
]