[
    {
        "uuid": "b115bca6-59af-4031-a764-50ca3b02382b",
        "userDefinedKey": "987680fd-035f-496f-1265-7a4c5258c11e",
        "concept": "Porifera",
        "height": 104,
        "observer": "yolov5",
        "width": 123,
        "x": 1049,
        "y": 371,
        "rejected": false,
        "verified": false,
        "lastUpdatedTimestamp": "2023-09-14T20:22:32.162Z"
    },
    {
        "uuid": "dfa22575-416d-4651-bfec-b6ce9107b230",
        "userDefinedKey": "58f8dc47-cf13-432e-0865-7a4c5258c11e",
        "concept": "Tunicata",
        "height": 38,
        "observer": "yolov5",
        "width": 41,
        "x": 1707,
        "y": 671,
        "rejected": false,
        "verified": false,
        "lastUpdatedTimestamp": "2023-09-14T20:22:32.162Z"
    },
    {
        "uuid": "72ac7011-fcd9-4540-be61-f2794aaf8789",
        "userDefinedKey": "30358443-d309-48a9-1a65-7a4c5258c11e",
        "concept": "Crinoidea",
        "height": 285,
        "observer": "yolov5",
        "width": 226,
        "x": 1052,
        "y": 771,
        "rejected": false,
        "verified": false,
        "lastUpdatedTimestamp": "2023-09-14T20:22:32.162Z"
    },
    {
        "uuid": "ce718c74-0262-47fd-bee1-828b0e7a8c2e",
        "userDefinedKey": "62a18287-3e27-4f97-1465-7a4c5258c11e",
        "concept": "Ophiuroidea",
        "height": 112,
        "observer": "yolov5",
        "width": 110,
        "x": 1457,
        "y": 92,
        "rejected": false,
        "verified": false,
        "lastUpdatedTimestamp": "2023-09-14T20:22:32.170Z"
    },
    {
        "uuid": "70b0d27c-8fb6-4040-a0b4-306c6efa80d4",
        "userDefinedKey": "0a75a6a4-7c64-4a06-0a65-7a4c5258c11e",
        "concept": "Ophiuroidea",
        "height": 79,
        "observer": "yolov5",
        "width": 92,
        "x": 1757,
        "y": 285,
        "rejected": false,
        "verified": false,
        "lastUpdatedTimestamp": "2023-09-14T20:22:32.170Z"
    },
    {
        "uuid": "cb9a56cc-640d-4249-a7c2-1d62e8497bac",
        "userDefinedKey": "4e6e21e9-073e-4c68-0c65-7a4c5258c11e",
        "concept": "Ophiuroidea",
        "height": 100,
        "observer": "yolov5",
        "width": 107,
        "x": 1510,
        "y": 440,
        "rejected": false,
        "verified": false,
        "lastUpdatedTimestamp": "2023-09-14T20:22:32.170Z"
    },
    {
        "uuid": "e526770b-255f-41ac-b86a-6776fddcb1f5",
        "userDefinedKey": "0eafaf5d-f2db-4d56-1865-7a4c5258c11e",
        "concept": "Ophiuroidea",
        "height": 103,
        "observer": "yolov5",
        "width": 118,
        "x": 1384,
        "y": 226,
        "rejected": false,
        "verified": false,
        "lastUpdatedTimestamp": "2023-09-14T20:22:32.170Z"
    },
    {
        "uuid": "ce31baad-2e1c-4026-99f0-8c3cd87b5849",
        "userDefinedKey": "349dba74-1e42-4cc1-1665-7a4c5258c11e",
        "concept": "Porifera",
        "height": 204,
        "observer": "yolov5",
        "width": 150,
        "x": 533,
        "y": 651,
        "rejected": false,
        "verified": false,
        "lastUpdatedTimestamp": "2023-09-14T20:22:32.170Z"
    },
    {
        "uuid": "0bc3b512-582e-466a-93ff-e77117a72a0b",
        "userDefinedKey": "db631008-a426-41c8-1065-7a4c5258c11e",
        "concept": "Ophiuroidea",
        "height": 91,
        "observer": "yolov5",
        "width": 96,
        "x": 1299,
        "y": 326,
        "rejected": false,
        "verified": false,
        "lastUpdatedTimestamp": "2023-09-14T20:22:32.170Z"
    },
    {
        "uuid": "2a95f8ed-1ce6-4a55-b4f0-5b1fb63566b0",
        "userDefinedKey": "d257b32b-ca19-470d-0665-7a4c5258c11e",
        "concept": "Ophiuroidea",
        "height": 69,
        "observer": "yolov5",
        "width": 76,
        "x": 1631,
        "y": 333,
        "rejected": false,
        "verified": false,
        "lastUpdatedTimestamp": "2023-09-14T20:22:32.170Z"
    }
]