[
    {
        "uuid": "ee88c5b7-7d21-4100-b16d-8fcc3ceb9c69",
        "userDefinedKey": "9cdb6fd4-c6e1-429c-ba6d-16683bc5aa1e",
        "concept": "Ophiuroidea",
        "height": 161,
        "observer": "expert-observer",
        "width": 156,
        "x": 419,
        "y": 285,
        "rejected": false,
        "verified": false,
        "lastUpdatedTimestamp": "2021-09-29T21:22:53.219Z"
    },
    {
        "uuid": "0037a401-ced4-44a4-bdd4-c294f8ef6dfa",
        "userDefinedKey": "6ec0ca6a-7ebb-4043-5a60-b0663bc5aa1e",
        "concept": "Porifera",
        "height": 55,
        "observer": "expert-observer",
        "width": 60,
        "x": 1691,
        "y": 459,
        "rejected": false,
        "verified": false,
        "lastUpdatedTimestamp": "2021-09-29T21:22:53.219Z"
    },
    {
        "uuid": "b9ace51e-7272-45d0-ab7d-c2cd53db8d32",
        "userDefinedKey": "879a2d23-0b7f-429f-e264-5d673bc5aa1e",
        "concept": "Asbestopluma",
        "height": 103,
        "observer": "expert-observer",
        "width": 148,
        "x": 1475,
        "y": 126,
        "rejected": false,
        "verified": false,
        "lastUpdatedTimestamp": "2021-09-29T21:22:53.219Z"
    },
    {
        "uuid": "7404950b-47e6-4b26-8ea1-603d2e03e01a",
        "userDefinedKey": "aa8cc691-1dc6-4016-6a63-25673bc5aa1e",
        "concept": "Asbestopluma",
        "height": 31,
        "observer": "expert-observer",
        "width": 88,
        "x": 367,
        "y": 516,
        "rejected": false,
        "verified": false,
        "lastUpdatedTimestamp": "2021-09-29T21:22:53.219Z"
    },
    {
        "uuid": "0e88f7a3-1099-423c-9e4b-c8adcc9dac3c",
        "userDefinedKey": "46184026-360e-472b-3e6f-44673bc5aa1e",
        "concept": "Acanthascinae",
        "height": 145,
        "observer": "expert-observer",
        "width": 105,
        "x": 1731,
        "y": 268,
        "rejected": false,
        "verified": false,
        "lastUpdatedTimestamp": "2021-09-29T21:22:53.219Z"
    },
    {
        "uuid": "fa9deae8-1de6-45f4-91d0-d4797489e5af",
        "userDefinedKey": "a4f17f2d-009c-4503-2e6c-cf663bc5aa1e",
        "concept": "Porifera",
        "height": 62,
        "observer": "expert-observer",
        "width": 87,
        "x": 1447,
        "y": 879,
        "rejected": false,
        "verified": false,
        "lastUpdatedTimestamp": "2021-09-29T21:22:53.219Z"
    },
    {
        "uuid": "89f255b9-6dca-4814-8028-e6bfe7bb1619",
        "userDefinedKey": "02636044-4606-4043-7664-73673bc5aa1e",
        "concept": "Asbestopluma",
        "height": 120,
        "observer": "expert-observer",
        "width": 125,
        "x": 1433,
        "y": 162,
        "rejected": false,
        "verified": false,
        "lastUpdatedTimestamp": "2021-09-29T21:22:53.219Z"
    },
    {
        "uuid": "15fc0814-a1d4-449d-afa9-cba536117cb4",
        "userDefinedKey": "3121e90c-65b4-4f37-1967-3a653bc5aa1e",
        "concept": "Sebastolobus",
        "height": 114,
        "observer": "linda",
        "width": 158,
        "x": 822,
        "y": 65,
        "rejected": false,
        "verified": false,
        "lastUpdatedTimestamp": "2021-09-29T21:22:53.219Z"
    },
    {
        "uuid": "d6436769-8741-41d2-90a6-22890442c1f6",
        "userDefinedKey": "28a96c98-0011-49b6-2e63-b5673bc5aa1e",
        "concept": "Asbestopluma",
        "height": 145,
        "observer": "expert-observer",
        "width": 131,
        "x": 1346,
        "y": 669,
        "rejected": false,
        "verified": false,
        "lastUpdatedTimestamp": "2021-09-29T21:22:53.219Z"
    },
    {
        "uuid": "534c8de2-2bdf-42bd-b1cd-a75bd9920468",
        "userDefinedKey": "20be3882-ddcf-42e9-1667-fe673bc5aa1e",
        "concept": "Ophiuroidea",
        "height": 141,
        "observer": "expert-observer",
        "width": 170,
        "x": 564,
        "y": 501,
        "rejected": false,
        "verified": false,
        "lastUpdatedTimestamp": "2021-09-29T21:22:53.223Z"
    },
    {
        "uuid": "aee3a771-d16d-468f-a771-edca620ef691",
        "userDefinedKey": "3a246643-bace-4b5b-e260-d0673bc5aa1e",
        "concept": "Ophiuroidea",
        "height": 66,
        "observer": "expert-observer",
        "width": 116,
        "x": 928,
        "y": 276,
        "rejected": false,
        "verified": false,
        "lastUpdatedTimestamp": "2021-09-29T21:22:53.223Z"
    },
    {
        "uuid": "3b70f26c-f00a-4324-b59c-f8fcbb481d38",
        "userDefinedKey": "b86cfc44-2596-4b95-c66c-0c673bc5aa1e",
        "concept": "Asbestopluma",
        "height": 57,
        "observer": "expert-observer",
        "width": 72,
        "x": 390,
        "y": 390,
        "rejected": false,
        "verified": false,
        "lastUpdatedTimestamp": "2021-09-29T21:22:53.223Z"
    },
    {
        "uuid": "678529d6-868c-43b3-8690-088b9147a3f3",
        "userDefinedKey": "59935844-4364-4ab9-4264-f9663bc5aa1e",
        "concept": "Porifera",
        "height": 898,
        "observer": "expert-observer",
        "width": 435,
        "x": 1,
        "y": 2,
        "rejected": false,
        "verified": false,
        "lastUpdatedTimestamp": "2021-09-29T21:22:53.223Z"
    },
    {
        "uuid": "bfd758be-4629-4a9a-bdef-b288bb4b89f3",
        "userDefinedKey": "ff91a0a7-d6ed-4f6a-2a62-8e673bc5aa1e",
        "concept": "Asbestopluma",
        "height": 89,
        "observer": "expert-observer",
        "width": 112,
        "x": 1438,
        "y": 229,
        "rejected": false,
        "verified": false,
        "lastUpdatedTimestamp": "2021-09-29T21:22:53.223Z"
    }
]