[
    {
        "uuid": "d393c4ef-5314-4dad-af00-ae6954176ca8",
        "userDefinedKey": "93b086e7-661d-4c07-1b65-48ee8a58c11e",
        "concept": "Ophiuroidea",
        "height": 28,
        "observer": "yolov5",
        "width": 32,
        "x": 317,
        "y": 32,
        "rejected": false,
        "verified": false,
        "lastUpdatedTimestamp": "2023-09-14T20:23:19.838Z"
    },
    {
        "uuid": "c647f7ec-c6c4-4e4d-81fd-80d397042c1d",
        "userDefinedKey": "6de84c70-4208-41e6-096e-45ee8a58c11e",
        "concept": "Ophiuroidea",
        "height": 23,
        "observer": "yolov5",
        "width": 29,
        "x": 182,
        "y": 133,
        "rejected": false,
        "verified": false,
        "lastUpdatedTimestamp": "2023-09-14T20:23:19.838Z"
    },
    {
        "uuid": "eb899ad2-e9fe-497d-8f71-80519c944df3",
        "userDefinedKey": "22dc1b19-30a8-4545-036e-45ee8a58c11e",
        "concept": "Ophiuroidea",
        "height": 27,
        "observer": "yolov5",
        "width": 33,
        "x": 130,
        "y": 120,
        "rejected": false,
        "verified": false,
        "lastUpdatedTimestamp": "2023-09-14T20:23:19.838Z"
    },
    {
        "uuid": "c104cb30-a9ab-43d4-9bf3-5b3db56e38a1",
        "userDefinedKey": "36d8182d-07c4-4d75-2165-48ee8a58c11e",
        "concept": "Ophiuroidea",
        "height": 47,
        "observer": "yolov5",
        "width": 56,
        "x": 413,
        "y": 421,
        "rejected": false,
        "verified": false,
        "lastUpdatedTimestamp": "2023-09-14T20:23:19.838Z"
    },
    {
        "uuid": "c004f1c1-dbc1-48bf-895c-9553f30f9339",
        "userDefinedKey": "6447ae7e-6369-4764-1f65-48ee8a58c11e",
        "concept": "Asteroidea",
        "height": 24,
        "observer": "yolov5",
        "width": 27,
        "x": 333,
        "y": 8,
        "rejected": false,
        "verified": false,
        "lastUpdatedTimestamp": "2023-09-14T20:23:19.838Z"
    },
    {
        "uuid": "54d6f4b6-a5f0-4ab0-a007-dd580c889d90",
        "userDefinedKey": "5c007a92-b503-4eb6-1d65-48ee8a58c11e",
        "concept": "Ophiuroidea",
        "height": 28,
        "observer": "yolov5",
        "width": 33,
        "x": 109,
        "y": 171,
        "rejected": false,
        "verified": false,
        "lastUpdatedTimestamp": "2023-09-14T20:23:19.838Z"
    },
    {
        "uuid": "a304fd1a-7173-4bda-82f0-df6b9ac3def7",
        "userDefinedKey": "0a306347-7d07-48b0-056e-45ee8a58c11e",
        "concept": "Ophiuroidea",
        "height": 34,
        "observer": "yolov5",
        "width": 42,
        "x": 426,
        "y": 19,
        "rejected": false,
        "verified": false,
        "lastUpdatedTimestamp": "2023-09-14T20:23:19.838Z"
    },
    {
        "uuid": "ccdac115-0224-4766-906a-de649be6abce",
        "userDefinedKey": "a0b851ec-7d5c-4621-076e-45ee8a58c11e",
        "concept": "Ophiuroidea",
        "height": 29,
        "observer": "yolov5",
        "width": 32,
        "x": 200,
        "y": 153,
        "rejected": false,
        "verified": false,
        "lastUpdatedTimestamp": "2023-09-14T20:23:19.838Z"
    }
]